MANIFEST.in
README.txt
setup.py
worldstock/__init__.py
worldstock/utils.py
worldstock/worldstock_function.py
worldstock.egg-info/PKG-INFO
worldstock.egg-info/SOURCES.txt
worldstock.egg-info/dependency_links.txt
worldstock.egg-info/requires.txt
worldstock.egg-info/top_level.txt
worldstock/dataset/brazil_name_dataset.csv
worldstock/dataset/brazil_refine_name_dataset.csv
worldstock/dataset/brazil_yahoo_dataset.csv
worldstock/dataset/china_name_dataset.csv
worldstock/dataset/china_refine_name_dataset.csv
worldstock/dataset/china_yahoo_dataset.csv
worldstock/dataset/hongkong_name_dataset.csv
worldstock/dataset/hongkong_refine_name_dataset.csv
worldstock/dataset/hongkong_yahoo_dataset.csv
worldstock/dataset/india_name_dataset.csv
worldstock/dataset/india_refine_name_dataset.csv
worldstock/dataset/india_yahoo_dataset.csv
worldstock/dataset/italy_name_dataset.csv
worldstock/dataset/italy_refine_name_dataset.csv
worldstock/dataset/italy_yahoo_dataset.csv
worldstock/dataset/japan_name_dataset.csv
worldstock/dataset/japan_refine_name_dataset.csv
worldstock/dataset/japan_yahoo_dataset.csv
worldstock/dataset/korea_name_dataset.csv
worldstock/dataset/korea_refine_name_dataset.csv
worldstock/dataset/korea_yahoo_dataset.csv
worldstock/dataset/spain_name_dataset.csv
worldstock/dataset/spain_refine_name_dataset.csv
worldstock/dataset/spain_yahoo_dataset.csv
worldstock/dataset/uk_name_dataset.csv
worldstock/dataset/uk_refine_name_dataset.csv
worldstock/dataset/uk_yahoo_dataset.csv
worldstock/dataset/us_name_dataset.csv
worldstock/dataset/us_refine_name_dataset.csv
worldstock/dataset/us_yahoo_dataset.csv
worldstock/dataset/words_470k.txt
worldstock/dataset/yahoo_country_code.json