Metadata-Version: 2.1
Name: worldstock
Version: 0.1.3
Summary: Download world stock list and Make short company name using full name
Home-page: http://github.com/2ky1234
Author: LEE GUNYOUNG
Author-email: 2ky1234@khu.ac.kr
License: MIT
Keywords: stock,data-analysis,company-info
Classifier: Programming Language :: Python :: 3
Requires-Python: >=3.9
